Workbook

Sheet Assumptions
A1: SaaS Revenue Model — Assumptions
A3: Starting MRR (USD) | B3: 85000
A4: Monthly growth rate | B4: 0.06
A5: Gross margin | B5: 0.78
A6: Monthly churn | B6: 0.021
A7: CAC per customer (USD) | B7: 1350

Sheet Projections
A1: 12-Month Projection
A3: Month | B3: MRR | C3: Revenue | D3: Gross Profit | E3: GP Margin
A4: 2026-01 | B4: =Assumptions!$B$3 -> 85000 | C4: =B4 -> 85000 | D4: =C4*Assumptions!$B$5 -> 66300 | E4: =D4/C4 -> 0.78
A5: 2026-02 | B5: =B4*(1+Assumptions!$B$4) -> 90100 | C5: =B5 -> 90100 | D5: =C5*Assumptions!$B$5 -> 70278 | E5: =D5/C5 -> 0.78
A6: 2026-03 | B6: =B5*(1+Assumptions!$B$4) -> 95506 | C6: =B6 -> 95506 | D6: =C6*Assumptions!$B$5 -> 74494.68 | E6: =D6/C6 -> 0.78
A7: 2026-04 | B7: =B6*(1+Assumptions!$B$4) -> 101236.36 | C7: =B7 -> 101236.36 | D7: =C7*Assumptions!$B$5 -> 78964.361 | E7: =D7/C7 -> 0.78
A8: 2026-05 | B8: =B7*(1+Assumptions!$B$4) -> 107310.54 | C8: =B8 -> 107310.54 | D8: =C8*Assumptions!$B$5 -> 83702.222 | E8: =D8/C8 -> 0.78
A9: 2026-06 | B9: =B8*(1+Assumptions!$B$4) -> 113749.17 | C9: =B9 -> 113749.17 | D9: =C9*Assumptions!$B$5 -> 88724.356 | E9: =D9/C9 -> 0.78
A10: 2026-07 | B10: =B9*(1+Assumptions!$B$4) -> 120574.12 | C10: =B10 -> 120574.12 | D10: =C10*Assumptions!$B$5 -> 94047.817 | E10: =D10/C10 -> 0.78
A11: 2026-08 | B11: =B10*(1+Assumptions!$B$4) -> 127808.57 | C11: =B11 -> 127808.57 | D11: =C11*Assumptions!$B$5 -> 99690.686 | E11: =D11/C11 -> 0.78
A12: 2026-09 | B12: =B11*(1+Assumptions!$B$4) -> 135477.09 | C12: =B12 -> 135477.09 | D12: =C12*Assumptions!$B$5 -> 105672.13 | E12: =D12/C12 -> 0.78
A13: 2026-10 | B13: =B12*(1+Assumptions!$B$4) -> 143605.71 | C13: =B13 -> 143605.71 | D13: =C13*Assumptions!$B$5 -> 112012.45 | E13: =D13/C13 -> 0.78
A14: 2026-11 | B14: =B13*(1+Assumptions!$B$4) -> 152222.05 | C14: =B14 -> 152222.05 | D14: =C14*Assumptions!$B$5 -> 118733.2 | E14: =D14/C14 -> 0.78
A15: 2026-12 | B15: =B14*(1+Assumptions!$B$4) -> 161355.38 | C15: =B15 -> 161355.38 | D15: =C15*Assumptions!$B$5 -> 125857.19 | E15: =D15/C15 -> 0.78
A16: Total | C16: =SUM(C4:C15) -> 1433945 | D16: =SUM(D4:D15) -> 1118477.1 | E16: =D16/C16 -> 0.78
